{
  "verbs": [
    {
      "infinitive": "bleiben",
      "pastTense": "blieb",
      "pastParticiple": "ist geblieben",
      "vowel1": "ei",
      "vowel2": "ie",
      "vowel21": "i",
      "vowel22": "e",
      "vowel3": "ie",
      "vowel31": "i",
      "vowel32": "e",
      "sentence": "Bleibt das Tier hier?",
      "sentence1": "Belibt das T",
      "sentence2": "r hier?",
      "sentence3": "",
      "infinitive1": "bl",
      "infinitive2": "ben",
      "pastTense1": "bl",
      "pastTense2": "b",
      "pastParticiple0": "ist",
      "pastParticiple1": "gebl",
      "pastParticiple2": "ben"
    },
    {
      "infinitive": "essen",
      "pastTense": "aß",
      "pastParticiple": "hat gegessen",
      "vowel1": "e",
      "vowel2": "a",
      "vowel21": "a",
      "vowel22": "",
      "vowel3": "e",
      "vowel31": "e",
      "vowel32": "",
      "sentence": "Die Bauern essen einen Apfel",
      "sentence1": "Die Bauern essen einen ",
      "sentence2": "pf",
      "sentence3": "",
      "sentence4": "l",
      "infinitive1": "ess",
      "infinitive2": "n",
      "pastTense1": "",
      "pastTense2": "ß",
      "pastParticiple0": "hat",
      "pastParticiple1": "geg",
      "pastParticiple2": "ssen",
      "image": ""
    },
    {
      "infinitive": "scheiden",
      "pastTense": "schied",
      "pastParticiple": "hat/ist geschieden",
      "vowel1": "ei",
      "vowel2": "ie",
      "vowel21": "i",
      "vowel22": "e",
      "vowel3": "ie",
      "vowel31": "i",
      "vowel32": "e",
      "sentence": "Wieviel mal scheidest du dich noch?",
      "sentence1": "",
      "sentence2": "",
      "sentence3": "",
      "infinitive1": "sh",
      "infinitive2": "den",
      "pastTense1": "sch",
      "pastTense2": "d",
      "pastParticiple0": "hat/ist",
      "pastParticiple1": "gesch",
      "pastParticiple2": "den"
    },
    {
      "infinitive": "fallen",
      "pastTense": "fiel",
      "pastParticiple": "ist gefallen",
      "vowel1": "a",
      "vowel2": "ie",
      "vowel21": "i",
      "vowel22": "e",
      "vowel3": "a",
      "vowel31": "a",
      "vowel32": "",
      "sentence": "Niemand ist gefallen",
      "sentence1": "N",
      "sentence2": "m",
      "sentence3": "nd ist gefallen",
      "infinitive1": "f",
      "infinitive2": "llen",
      "pastTense1": "f",
      "pastTense2": "l",
      "pastParticiple0": "ist",
      "pastParticiple1": "gef",
      "pastParticiple2": "llen"
    },
    {
      "infinitive": "finden",
      "pastTense": "fand",
      "pastParticiple": "hat gefunden",
      "vowel1": "i",
      "vowel2": "a",
      "vowel21": "a",
      "vowel22": "",
      "vowel3": "u",
      "vowel31": "u",
      "vowel32": "",
      "sentence": "Ich habe ein blaues Auto gefunden",
      "sentence1": "Ich habe ein bl",
      "sentence2": "",
      "sentence3": "es Auto gefunden!",
      "infinitive1": "f",
      "infinitive2": "nden",
      "pastTense1": "f",
      "pastTense2": "nd",
      "pastParticiple0": "hat",
      "pastParticiple1": "gef",
      "pastParticiple2": "nden"
    }
    ,
    {
      "infinitive": "geben",
      "pastTense": "gab",
      "pastParticiple": "hat gegeben",
      "vowel1": "e",
      "vowel2": "a",
      "vowel21": "a",
      "vowel22": "",
      "vowel3": "e",
      "vowel31": "e",
      "vowel32": "",
      "sentence": "Ich gebe dir mein Lader",
      "sentence1": "Ich gebe dir mein L",
      "sentence2": "d",
      "sentence3": "r",
      "infinitive1": "geb",
      "infinitive2": "n",
      "pastTense1": "g",
      "pastTense2": "b",
      "pastParticiple0": "hat",
      "pastParticiple1": "geg",
      "pastParticiple2": "ben"
    }
    ,
    {
      "infinitive": "gehen",
      "pastTense": "ging",
      "pastParticiple": "ist gegangen",
      "vowel1": "e",
      "vowel2": "i",
      "vowel21": "i",
      "vowel22": "",
      "vowel3": "a",
      "vowel31": "a",
      "vowel32": "",
      "sentence": "Ich gehe zum Seminar",
      "sentence1": "Ich gehe zum Sem",
      "sentence2": "n",
      "sentence3": "r",
      "infinitive1": "geh",
      "infinitive2": "n",
      "pastTense1": "g",
      "pastTense2": "ng",
      "pastParticiple0": "ist",
      "pastParticiple1": "geg",
      "pastParticiple2": "ngen"
    }
    ,
    {
      "infinitive": "gewinnen",
      "pastTense": "gewann",
      "pastParticiple": "hat gewonnen",
      "vowel1": "i",
      "vowel2": "a",
      "vowel21": "a",
      "vowel22": "",
      "vowel3": "o",
      "vowel31": "o",
      "vowel32": "",
      "sentence": "Ich habe ein Abo gewonnen",
      "sentence1": "Ich habe ein ",
      "sentence2": "b",
      "sentence3": " gewonnen",
      "infinitive1": "gew",
      "infinitive2": "nnen",
      "pastTense1": "gew",
      "pastTense2": "nn",
      "pastParticiple0": "hat",
      "pastParticiple1": "gew",
      "pastParticiple2": "nnen"
    }
    ,
    {
      "infinitive": "halten",
      "pastTense": "hielt",
      "pastParticiple": "hat gehalten",
      "vowel1": "a",
      "vowel2": "ie",
      "vowel21": "i",
      "vowel22": "e",
      "vowel3": "a",
      "vowel31": "a",
      "vowel32": "",
      "sentence": "Ich halte Siena für schön",
      "sentence1": "Ich halte S",
      "sentence2": "n",
      "sentence3": " für schön",
      "infinitive1": "h",
      "infinitive2": "lten",
      "pastTense1": "h",
      "pastTense2": "lt",
      "pastParticiple0": "hat",
      "pastParticiple1": "geh",
      "pastParticiple2": "lten"
    }
    ,
    {
      "infinitive": "heißen",
      "pastTense": "hieß",
      "pastParticiple": "hat geheißen",
      "vowel1": "ei",
      "vowel2": "ie",
      "vowel21": "i",
      "vowel22": "e",
      "vowel3": "ei",
      "vowel31": "e",
      "vowel32": "i",
      "sentence": "Die Tibeterin heißt Dolma",
      "sentence1": "Die T",
      "sentence2": "b",
      "sentence3": "t",
      "sentence4": "r",
      "sentence5": "n heißt Dolma",
      "infinitive1": "h",
      "infinitive2": "ßen",
      "pastTense1": "h",
      "pastTense2": "ß",
      "pastParticiple0": "hat",
      "pastParticiple1": "geh",
      "pastParticiple2": "ßen"
    }
    ,
    {
      "infinitive": "helfen",
      "pastTense": "half",
      "pastParticiple": "hat geholfen",
      "vowel1": "e",
      "vowel2": "a",
      "vowel21": "a",
      "vowel22": "",
      "vowel3": "o",
      "vowel31": "o",
      "vowel32": "",
      "sentence": "Kakao hilft beim kochen",
      "infinitive1": "h",
      "infinitive2": "lfen",
      "pastTense1": "h",
      "pastTense2": "lf",
      "pastParticiple0": "hat",
      "pastParticiple1": "geh",
      "pastParticiple2": "lfen"
    }
    ,
    {
      "infinitive": "kommen",
      "pastTense": "kam",
      "pastParticiple": "hat gekommen",
      "vowel1": "o",
      "vowel2": "a",
      "vowel21": "a",
      "vowel22": "",
      "vowel3": "o",
      "vowel31": "o",
      "vowel32": "",
      "sentence": "Amor ist gekommen!",
      "infinitive1": "k",
      "infinitive2": "mmen",
      "pastTense1": "k",
      "pastTense2": "m",
      "pastParticiple0": "hat",
      "pastParticiple1": "gk",
      "pastParticiple2": "mmen"
    }
    ,
    {
      "infinitive": "lassen",
      "pastTense": "ließ",
      "pastParticiple": "hat gelassen",
      "vowel1": "a",
      "vowel2": "ie",
      "vowel21": "i",
      "vowel22": "e",
      "vowel3": "a",
      "vowel31": "a",
      "vowel32": "",
      "sentence": "Lass das Mineral in Ruhe!",
      "infinitive1": "l",
      "infinitive2": "ssen",
      "pastTense1": "l",
      "pastTense2": "ß",
      "pastParticiple0": "hat",
      "pastParticiple1": "gel",
      "pastParticiple2": "ssen"
    }
    ,
    {
      "infinitive": "laufen",
      "pastTense": "lief",
      "pastParticiple": "hat gelaufen",
      "vowel1": "au",
      "vowel2": "ie",
      "vowel21": "i",
      "vowel2": "e",
      "vowel3": "au",
      "vowel31": "a",
      "vowel32": "u",
      "sentence": "Immer schneller laufen, niveauvoll laufen!",
      "infinitive1": "l",
      "infinitive2": "fen",
      "pastTense1": "l",
      "pastTense2": "f",
      "pastParticiple0": "hat",
      "pastParticiple1": "gel",
      "pastParticiple2": "fen"
    }
    ,
    {
      "infinitive": "liegen",
      "pastTense": "lag",
      "pastParticiple": "hat gelegen",
      "vowel1": "ie",
      "vowel2": "a",
      "vowel21": "a",
      "vowel22": "",
      "vowel3": "e",
      "vowel31": "e",
      "vowel32": "",
      "sentence": "Bayer liegt in Deutschland",
      "infinitive1": "l",
      "infinitive2": "gen",
      "pastTense1": "l",
      "pastTense2": "g",
      "pastParticiple0": "hat",
      "pastParticiple1": "gel",
      "pastParticiple2": "gen"
    }
    ,
    {
      "infinitive": "nehmen",
      "pastTense": "nahm",
      "pastParticiple": "hat genommen",
      "vowel1": "e",
      "vowel2": "a",
      "vowel21": "a",
      "vowel22": "",
      "vowel3": "o",
      "vowel31": "o",
      "vowel32": "",
      "sentence": "Nimmt das Fagott!",
      "infinitive1": "n",
      "infinitive2": "hmen",
      "pastTense1": "n",
      "pastTense2": "hm",
      "pastParticiple0": "hat",
      "pastParticiple1": "gen",
      "pastParticiple2": "mmen"
    }
    ,
    {
      "infinitive": "sehen",
      "pastTense": "sah",
      "pastParticiple": "hat gesehen",
      "vowel1": "e",
      "vowel2": "a",
      "vowel21": "a",
      "vowel22": "",
      "vowel3": "e",
      "vowel31": "e",
      "vowel32": "",
      "sentence": "Ich sehe zu viele Gabel",
      "infinitive1": "s",
      "infinitive2": "hen",
      "pastTense1": "s",
      "pastTense2": "h",
      "pastParticiple0": "hat",
      "pastParticiple1": "ges",
      "pastParticiple2": "hen"
    }
    ,
    {
      "infinitive": "sitzen",
      "pastTense": "saß",
      "pastParticiple": "hat gesessen",
      "vowel1": "i",
      "vowel2": "a",
      "vowel21": "a",
      "vowel22": "",
      "vowel3": "e",
      "vowel31": "e",
      "vowel32": "",
      "sentence": "Ich sitze auf dem Vater",
      "infinitive1": "s",
      "infinitive2": "tzen",
      "pastTense1": "s",
      "pastTense2": "ß",
      "pastParticiple0": "hat",
      "pastParticiple1": "ges",
      "pastParticiple2": "ssen"
    }
    ,
    {
      "infinitive": "sprechen",
      "pastTense": "sprach",
      "pastParticiple": "hat gesprochen",
      "vowel1": "e",
      "vowel2": "a",
      "vowel21": "a",
      "vowel22": "",
      "vowel3": "o",
      "vowel31": "o",
      "vowel32": "",
      "sentence": "Sie spricht über den Barock",
      "infinitive1": "spr",
      "infinitive2": "chen",
      "pastTense1": "spr",
      "pastTense2": "ch",
      "pastParticiple0": "hat",
      "pastParticiple1": "gespr",
      "pastParticiple2": "chen"
    }
    ,
    {
      "infinitive": "stehen",
      "pastTense": "stand",
      "pastParticiple": "hat gestanden",
      "vowel1": "e",
      "vowel2": "a",
      "vowel21": "a",
      "vowel22": "",
      "vowel3": "a",
      "vowel31": "a",
      "vowel32": "",
      "sentence": "Das Paar steht mit dem Fahrrad",
      "infinitive1": "st",
      "infinitive2": "hen",
      "pastTense1": "st",
      "pastTense2": "nd",
      "pastParticiple0": "hat",
      "pastParticiple1": "gest",
      "pastParticiple2": "nden"
    }
    ,
    {
      "infinitive": "tragen",
      "pastTense": "trug",
      "pastParticiple": "hat getragen",
      "vowel1": "a",
      "vowel2": "u",
      "vowel21": "u",
      "vowel22": "",
      "vowel3": "a",
      "vowel31": "a",
      "vowel32": "",
      "sentence": "In den USA trage ich Hut und Schal",
      "sentence1": "In den USA trage ich H",
      "sentence2": "t und Schal",
      "sentence3": "l",
      "infinitive1": "tr",
      "infinitive2": "gen",
      "pastTense1": "tr",
      "pastTense2": "g",
      "pastParticiple0": "hat",
      "pastParticiple1": "getr",
      "pastParticiple2": "gen"
    }
    ,
    {
      "infinitive": "tun",
      "pastTense": "tat",
      "pastParticiple": "hat getan",
      "vowel1": "u",
      "vowel2": "a",
      "vowel21": "a",
      "vowel22": "",
      "vowel3": "a",
      "vowel31": "a",
      "vowel32": "",
      "sentence": "Was tun Sie mit Tabak?",
      "sentence1": "Was tun Sie mit T",
      "sentence2": "b",
      "sentence3": "k?",
      "infinitive1": "t",
      "infinitive2": "n",
      "pastTense1": "t",
      "pastTense2": "t",
      "pastParticiple0": "hat",
      "pastParticiple1": "get",
      "pastParticiple2": "n"
    }
    ,
    {
      "infinitive": "verlieren",
      "pastTense": "verlor",
      "pastParticiple": "hat verloren",
      "vowel1": "ie",
      "vowel2": "o",
      "vowel21": "o",
      "vowel22": "",
      "vowel3": "o",
      "vowel31": "o",
      "vowel32": "",
      "sentence": "Ich habe dein Photo verloren",
      "sentence1": "Ich habe dein Pho",
      "sentence2": "t",
      "sentence3": " verloren",
      "infinitive1": "verl",
      "infinitive2": "ren",
      "pastTense1": "verl",
      "pastTense2": "r",
      "pastParticiple0": "hat",
      "pastParticiple1": "verl",
      "pastParticiple2": "ren"
    }
    ,
    {
      "infinitive": "ziehen",
      "pastTense": "zog",
      "pastParticiple": "hat/ist gezogen",
      "vowel1": "ie",
      "vowel2": "o",
      "vowel21": "o",
      "vowel22": "",
      "vowel3": "o",
      "vowel31": "o",
      "vowel32": "",
      "sentence": "Ein Doofe zieht mein Boot",
        "sentence1": "Ein Doofe zieht mein B",
          "sentence2": "",
            "sentence3": "t",
      "infinitive1": "z",
      "infinitive2": "hen",
      "pastTense1": "z",
      "pastTense2": "g",
      "pastParticiple0": "hat",
      "pastParticiple1": "gez",
      "pastParticiple2": "gen"
    }
  ]
}
